README
setup.py
nose_gevented_multiprocess/__init__.py
nose_gevented_multiprocess/nose_gevented_multiprocess.py
nose_gevented_multiprocess.egg-info/PKG-INFO
nose_gevented_multiprocess.egg-info/SOURCES.txt
nose_gevented_multiprocess.egg-info/dependency_links.txt
nose_gevented_multiprocess.egg-info/entry_points.txt
nose_gevented_multiprocess.egg-info/requires.txt
nose_gevented_multiprocess.egg-info/top_level.txt